{
    "plural":[
        {
            "name":"dm_incorrect_code",
            "value":[
                {
                    "quantity":"one",
                    "value":"गलत। %d प्रयास शेष है।",
                    "attr":{
                        "priority":"translate"
                    }
                },
                {
                    "quantity":"other",
                    "value":"गलत। %d प्रयास शेष हैं।",
                    "attr":{
                        "priority":"translate"
                    }
                }
            ]
        },
        {
            "name":"dm_not_allow",
            "value":[
                {
                    "quantity":"other",
                    "value":"भरोसा न करें (%d)",
                    "attr":{
                        "priority":"translate"
                    }
                },
                {
                    "quantity":"one",
                    "value":"भरोसा न करें (%d)",
                    "attr":{
                        "priority":"translate"
                    }
                }
            ]
        }
    ]
}