{
    "plural":[
        {
            "name":"dm_incorrect_code",
            "value":[
                {
                    "quantity":"other",
                    "value":"正しくありません。残り試行回数は%d回です。",
                    "attr":{
                        "priority":"LT"
                    }
                }
            ]
        },
        {
            "name":"dm_not_allow",
            "value":[
                {
                    "quantity":"other",
                    "value":"信頼しない（%d）",
                    "attr":{
                        "priority":"LT"
                    }
                }
            ]
        }
    ]
}