{
    "plural":[
        {
            "name":"dm_incorrect_code",
            "value":[
                {
                    "quantity":"one",
                    "value":"Nesprávně. Zbývá %d pokus.",
                    "attr":{
                        "priority":"translate"
                    }
                },
                {
                    "quantity":"other",
                    "value":"Nesprávně. Zbývá %d pokusů.",
                    "attr":{
                        "priority":"translate"
                    }
                },
                {
                    "quantity":"few",
                    "value":"Nesprávně. Zbývají %d pokusy.",
                    "attr":{
                        "priority":"translate"
                    }
                },
                {
                    "quantity":"many",
                    "value":"Nesprávně. Zbývá %d pokusů.",
                    "attr":{
                        "priority":"translate"
                    }
                }
            ]
        },
        {
            "name":"dm_not_allow",
            "value":[
                {
                    "quantity":"other",
                    "value":"Nedůvěřovat (%d)",
                    "attr":{
                        "priority":"translate"
                    }
                },
                {
                    "quantity":"one",
                    "value":"Nedůvěřovat (%d)",
                    "attr":{
                        "priority":"translate"
                    }
                },
                {
                    "quantity":"few",
                    "value":"Nedůvěřovat (%d)",
                    "attr":{
                        "priority":"translate"
                    }
                },
                {
                    "quantity":"many",
                    "value":"Nedůvěřovat (%d)",
                    "attr":{
                        "priority":"translate"
                    }
                }
            ]
        }
    ]
}